{"num_pairs":12,"pairs":[{"index":1,"nt1":"A.DC1","nt2":"C.DG26","bp":"C-G","name":"--","Saenger":"n/a","LW":"cWW","DSSR":"cW-W","chi1":-139.158,"conf1":"anti","pucker1":"~C2'-endo","lambda1":45.291,"chi2":-103.163,"conf2":"anti","pucker2":"~C2'-endo","lambda2":56.226,"C1C1_dist":9.806,"N1N9_dist":7.929,"C6C8_dist":8.590,"CNNC_torsion":6.483,"hbonds_num":1,"hbonds_desc":"N3-N2(amino)[2.35]","interBase_angle":2.325,"simple_Shear":-0.827,"simple_Stretch":-1.370,"simple_Buckle":-0.482,"simple_Propeller":2.274,"bp_params":[-0.702,-1.437,-0.261,-0.681,2.223,-8.103],"frame":{"rsmd":null,"origin":[1.667,-0.350,-1.248],"x_axis":[-0.860,0.293,-0.417],"y_axis":[-0.223,-0.952,-0.208],"z_axis":[-0.458,-0.086,0.885]}},{"index":2,"nt1":"A.DC2","nt2":"C.DG25","bp":"C-G","name":"WC","Saenger":"19-XIX","LW":"cWW","DSSR":"cW-W","chi1":-111.931,"conf1":"anti","pucker1":"~C2'-endo","lambda1":57.083,"chi2":-144.016,"conf2":"anti","pucker2":"~C2'-endo","lambda2":52.826,"C1C1_dist":10.671,"N1N9_dist":8.958,"C6C8_dist":9.800,"CNNC_torsion":3.753,"hbonds_num":3,"hbonds_desc":"O2(carbonyl)-N2(amino)[2.67],N3-N1(imino)[2.88],N4(amino)-O6(carbonyl)[2.88]","interBase_angle":7.724,"simple_Shear":0.415,"simple_Stretch":-0.188,"simple_Buckle":-7.703,"simple_Propeller":-0.569,"bp_params":[0.408,-0.204,0.003,-7.719,-0.272,-1.150],"frame":{"rsmd":null,"origin":[0.392,-0.544,3.415],"x_axis":[-0.826,-0.561,0.061],"y_axis":[0.558,-0.828,-0.055],"z_axis":[0.081,-0.011,0.997]}},{"index":3,"nt1":"A.DA3","nt2":"C.DT24","bp":"A-T","name":"WC","Saenger":"20-XX","LW":"cWW","DSSR":"cW-W","chi1":-93.650,"conf1":"anti","pucker1":"~C2'-endo","lambda1":54.128,"chi2":-82.897,"conf2":"anti","pucker2":"~C2'-endo","lambda2":54.003,"C1C1_dist":10.806,"N1N9_dist":9.056,"C6C8_dist":9.819,"CNNC_torsion":-35.430,"hbonds_num":2,"hbonds_desc":"N6(amino)-O4(carbonyl)[2.78],N1-N3(imino)[2.88]","interBase_angle":15.187,"simple_Shear":0.191,"simple_Stretch":-0.132,"simple_Buckle":-1.221,"simple_Propeller":-15.138,"bp_params":[0.188,-0.136,-0.237,-1.591,-15.103,-4.763],"frame":{"rsmd":null,"origin":[-0.149,0.308,6.747],"x_axis":[-0.331,-0.944,0.018],"y_axis":[0.938,-0.326,0.121],"z_axis":[-0.109,0.057,0.992]}},{"index":4,"nt1":"A.DA4","nt2":"C.DT23","bp":"A-T","name":"WC","Saenger":"20-XX","LW":"cWW","DSSR":"cW-W","chi1":-110.746,"conf1":"anti","pucker1":"~C2'-endo","lambda1":53.115,"chi2":-119.406,"conf2":"anti","pucker2":"~C2'-endo","lambda2":60.261,"C1C1_dist":10.462,"N1N9_dist":8.842,"C6C8_dist":9.718,"CNNC_torsion":-35.719,"hbonds_num":2,"hbonds_desc":"N6(amino)-O4(carbonyl)[2.81],N1-N3(imino)[2.80]","interBase_angle":11.304,"simple_Shear":-0.209,"simple_Stretch":-0.255,"simple_Buckle":1.755,"simple_Propeller":-11.167,"bp_params":[-0.205,-0.259,0.395,1.925,-11.139,-1.861],"frame":{"rsmd":null,"origin":[-0.316,0.421,9.706],"x_axis":[0.257,-0.965,0.059],"y_axis":[0.966,0.255,-0.032],"z_axis":[0.016,0.065,0.998]}},{"index":5,"nt1":"A.DG5","nt2":"C.DC22","bp":"G-C","name":"WC","Saenger":"19-XIX","LW":"cWW","DSSR":"cW-W","chi1":-146.442,"conf1":"anti","pucker1":"~C2'-endo","lambda1":53.670,"chi2":-120.302,"conf2":"anti","pucker2":"~C2'-endo","lambda2":58.599,"C1C1_dist":10.627,"N1N9_dist":8.950,"C6C8_dist":9.822,"CNNC_torsion":-4.306,"hbonds_num":3,"hbonds_desc":"O6(carbonyl)-N4(amino)[2.93],N1(imino)-N3[2.89],N2(amino)-O2(carbonyl)[2.66]","interBase_angle":9.544,"simple_Shear":-0.536,"simple_Stretch":-0.198,"simple_Buckle":3.557,"simple_Propeller":-8.856,"bp_params":[-0.526,-0.225,0.164,3.992,-8.669,-0.420],"frame":{"rsmd":null,"origin":[-0.805,0.234,13.040],"x_axis":[0.760,-0.642,0.099],"y_axis":[0.649,0.752,-0.116],"z_axis":[0.000,0.152,0.988]}},{"index":6,"nt1":"A.DG6","nt2":"C.DC21","bp":"G-C","name":"WC","Saenger":"19-XIX","LW":"cWW","DSSR":"cW-W","chi1":-143.082,"conf1":"anti","pucker1":"....","lambda1":50.734,"chi2":-124.985,"conf2":"anti","pucker2":"~C2'-endo","lambda2":53.464,"C1C1_dist":10.842,"N1N9_dist":9.005,"C6C8_dist":9.791,"CNNC_torsion":22.861,"hbonds_num":3,"hbonds_desc":"O6(carbonyl)-N4(amino)[2.85],N1(imino)-N3[2.85],N2(amino)-O2(carbonyl)[2.67]","interBase_angle":10.319,"simple_Shear":-0.166,"simple_Stretch":-0.197,"simple_Buckle":-9.511,"simple_Propeller":4.003,"bp_params":[-0.163,-0.200,-0.414,-9.570,3.861,-2.837],"frame":{"rsmd":null,"origin":[-1.193,-0.863,16.933],"x_axis":[0.991,-0.100,0.087],"y_axis":[0.107,0.991,-0.084],"z_axis":[-0.078,0.093,0.993]}},{"index":7,"nt1":"B.DC8","nt2":"C.DG19","bp":"C-G","name":"WC","Saenger":"19-XIX","LW":"cWW","DSSR":"cW-W","chi1":-150.154,"conf1":"anti","pucker1":"~C2'-endo","lambda1":56.100,"chi2":-130.765,"conf2":"anti","pucker2":"~C2'-endo","lambda2":50.710,"C1C1_dist":10.707,"N1N9_dist":8.926,"C6C8_dist":9.677,"CNNC_torsion":0.075,"hbonds_num":3,"hbonds_desc":"O2(carbonyl)-N2(amino)[2.73],N3-N1(imino)[2.90],N4(amino)-O6(carbonyl)[2.79]","interBase_angle":1.777,"simple_Shear":0.656,"simple_Stretch":-0.321,"simple_Buckle":-1.371,"simple_Propeller":-1.130,"bp_params":[0.635,-0.361,0.437,-1.438,-1.044,-4.880],"frame":{"rsmd":null,"origin":[-0.391,0.067,23.938],"x_axis":[0.210,0.977,-0.032],"y_axis":[-0.974,0.206,-0.096],"z_axis":[-0.088,0.052,0.995]}},{"index":8,"nt1":"B.DT9","nt2":"C.DA18","bp":"T-A","name":"WC","Saenger":"20-XX","LW":"cWW","DSSR":"cW-W","chi1":-99.055,"conf1":"anti","pucker1":"~C2'-endo","lambda1":56.693,"chi2":-116.895,"conf2":"anti","pucker2":"~C2'-endo","lambda2":50.748,"C1C1_dist":10.636,"N1N9_dist":8.857,"C6C8_dist":9.710,"CNNC_torsion":9.223,"hbonds_num":2,"hbonds_desc":"N3(imino)-N1[2.85],O4(carbonyl)-N6(amino)[2.86]","interBase_angle":8.390,"simple_Shear":0.199,"simple_Stretch":-0.237,"simple_Buckle":5.718,"simple_Propeller":-6.139,"bp_params":[0.195,-0.240,0.409,5.622,-6.228,-3.007],"frame":{"rsmd":null,"origin":[0.030,0.472,27.280],"x_axis":[-0.331,0.938,0.103],"y_axis":[-0.943,-0.324,-0.076],"z_axis":[-0.038,-0.123,0.992]}},{"index":9,"nt1":"B.DT10","nt2":"C.DA17","bp":"T-A","name":"WC","Saenger":"20-XX","LW":"cWW","DSSR":"cW-W","chi1":-152.685,"conf1":"anti","pucker1":"~C2'-endo","lambda1":53.252,"chi2":-73.888,"conf2":"anti","pucker2":"~C2'-endo","lambda2":54.555,"C1C1_dist":10.546,"N1N9_dist":8.789,"C6C8_dist":9.536,"CNNC_torsion":-26.031,"hbonds_num":2,"hbonds_desc":"N3(imino)-N1[2.67],O4(carbonyl)-N6(amino)[2.52]","interBase_angle":8.720,"simple_Shear":-0.121,"simple_Stretch":-0.411,"simple_Buckle":-4.276,"simple_Propeller":-7.600,"bp_params":[-0.115,-0.413,0.535,-4.145,-7.672,-7.367],"frame":{"rsmd":null,"origin":[0.413,-0.099,30.870],"x_axis":[-0.817,0.576,-0.044],"y_axis":[-0.572,-0.817,-0.070],"z_axis":[-0.076,-0.032,0.997]}},{"index":10,"nt1":"B.DG11","nt2":"C.DC16","bp":"G-C","name":"WC","Saenger":"19-XIX","LW":"cWW","DSSR":"cW-W","chi1":-75.466,"conf1":"anti","pucker1":"~C2'-endo","lambda1":48.502,"chi2":-91.958,"conf2":"anti","pucker2":"~C2'-endo","lambda2":57.841,"C1C1_dist":10.613,"N1N9_dist":8.878,"C6C8_dist":9.572,"CNNC_torsion":-50.343,"hbonds_num":3,"hbonds_desc":"O6(carbonyl)-N4(amino)[2.60],N1(imino)-N3[2.75],N2(amino)-O2(carbonyl)[2.77]","interBase_angle":20.866,"simple_Shear":-0.117,"simple_Stretch":-0.390,"simple_Buckle":11.033,"simple_Propeller":-17.711,"bp_params":[-0.111,-0.392,0.632,11.291,-17.548,-8.188],"frame":{"rsmd":null,"origin":[0.402,-0.225,33.896],"x_axis":[-0.999,-0.043,-0.017],"y_axis":[0.042,-0.997,0.062],"z_axis":[-0.020,0.061,0.998]}},{"index":11,"nt1":"B.DG12","nt2":"C.DC15","bp":"G-C","name":"WC","Saenger":"19-XIX","LW":"cWW","DSSR":"cW-W","chi1":-132.326,"conf1":"anti","pucker1":"~C2'-endo","lambda1":51.208,"chi2":-116.133,"conf2":"anti","pucker2":"~C2'-endo","lambda2":50.438,"C1C1_dist":10.862,"N1N9_dist":8.978,"C6C8_dist":9.658,"CNNC_torsion":-32.532,"hbonds_num":3,"hbonds_desc":"O6(carbonyl)-N4(amino)[2.72],N1(imino)-N3[2.78],N2(amino)-O2(carbonyl)[2.68]","interBase_angle":18.974,"simple_Shear":0.063,"simple_Stretch":-0.318,"simple_Buckle":-6.535,"simple_Propeller":-17.813,"bp_params":[0.058,-0.319,0.374,-6.773,-17.724,-6.810],"frame":{"rsmd":null,"origin":[-0.153,-0.561,37.738],"x_axis":[-0.695,-0.713,0.089],"y_axis":[0.717,-0.681,0.148],"z_axis":[-0.045,0.167,0.985]}},{"index":12,"nt1":"B.DG13","nt2":"C.DC14","bp":"G-C","name":"WC","Saenger":"19-XIX","LW":"cWW","DSSR":"cW-W","chi1":-142.016,"conf1":"anti","pucker1":"~C2'-endo","lambda1":40.714,"chi2":-107.215,"conf2":"anti","pucker2":"~C2'-endo","lambda2":48.526,"C1C1_dist":10.690,"N1N9_dist":8.596,"C6C8_dist":9.003,"CNNC_torsion":-13.617,"hbonds_num":3,"hbonds_desc":"O6(carbonyl)-N4(amino)[2.26],N1(imino)-N3[2.80],N2(amino)-O2(carbonyl)[3.06]","interBase_angle":22.868,"simple_Shear":-1.088,"simple_Stretch":-0.675,"simple_Buckle":-20.491,"simple_Propeller":-10.153,"bp_params":[-1.015,-0.780,-0.455,-19.415,-12.084,-17.920],"frame":{"rsmd":null,"origin":[1.668,1.218,40.841],"x_axis":[-0.064,-0.955,0.289],"y_axis":[0.988,-0.101,-0.113],"z_axis":[0.137,0.279,0.951]}}],"num_helices":1,"helices":[{"index":1,"num_stems":2,"strand1":"CCAAGGCTTGGG","strand2":"GGTTCCGAACCC","bp_type":".|||||||||||","helix_form":".BBB.xBBBB.","helical_rise":3.579,"helical_rise_std":1.231,"helical_radius":9.693,"helical_radius_std":3.196,"helical_axis":[-0.192,0.240,0.952],"point1":[4.741,-4.168,0.627],"point2":[-2.799,5.227,37.951],"num_pairs":12,"pairs":[{"index":1,"nt1":"A.DC1","nt2":"C.DG26","bp":"C-G","name":"--","Saenger":"n/a","LW":"cWW","DSSR":"cW-W","bp1_params":[-0.702,-1.437,-0.261,-0.681,2.223,-8.103],"step_params":[0.323,-0.102,4.826,-0.597,-32.266,49.573],"heli_params":[2.452,-0.377,4.185,-34.604,0.641,58.590],"bp2_params":[0.408,-0.204,0.003,-7.719,-0.272,-1.150],"groove_widths":[null,null,null,null],"simple_Rise":4.826,"simple_Twist":43.854,"simple_hRise":4.026,"simple_hTwist":53.972},{"index":2,"nt1":"A.DC2","nt2":"C.DG25","bp":"C-G","name":"WC","Saenger":"19-XIX","LW":"cWW","DSSR":"cW-W","bp1_params":[0.408,-0.204,0.003,-7.719,-0.272,-1.150],"step_params":[-0.313,-0.865,3.358,11.024,3.548,36.590],"heli_params":[-1.763,1.862,3.047,5.485,-17.042,38.319],"bp2_params":[0.188,-0.136,-0.237,-1.591,-15.103,-4.763],"groove_widths":[null,null,null,null],"simple_Rise":3.358,"simple_Twist":36.003,"simple_hRise":3.040,"simple_hTwist":37.761},{"index":3,"nt1":"A.DA3","nt2":"C.DT24","bp":"A-T","name":"WC","Saenger":"20-XX","LW":"cWW","DSSR":"cW-W","bp1_params":[0.188,-0.136,-0.237,-1.591,-15.103,-4.763],"step_params":[0.069,-0.026,2.966,-7.115,-0.722,34.308],"heli_params":[0.056,-1.084,2.894,-1.208,11.902,35.023],"bp2_params":[-0.205,-0.259,0.395,1.925,-11.139,-1.861],"groove_widths":[10.372,null,17.226,null],"simple_Rise":2.966,"simple_Twist":37.875,"simple_hRise":2.906,"simple_hTwist":38.520},{"index":4,"nt1":"A.DA4","nt2":"C.DT23","bp":"A-T","name":"WC","Saenger":"20-XX","LW":"cWW","DSSR":"cW-W","bp1_params":[-0.205,-0.259,0.395,1.925,-11.139,-1.861],"step_params":[0.188,-0.727,3.289,-1.930,-4.733,34.593],"heli_params":[-0.483,-0.610,3.342,-7.905,3.224,34.957],"bp2_params":[-0.526,-0.225,0.164,3.992,-8.669,-0.420],"groove_widths":[13.507,11.258,19.185,19.068],"simple_Rise":3.289,"simple_Twist":36.259,"simple_hRise":3.341,"simple_hTwist":36.605},{"index":5,"nt1":"A.DG5","nt2":"C.DC22","bp":"G-C","name":"WC","Saenger":"19-XIX","LW":"cWW","DSSR":"cW-W","bp1_params":[-0.526,-0.225,0.164,3.992,-8.669,-0.420],"step_params":[0.399,-1.534,3.742,4.911,-2.758,34.195],"heli_params":[-2.080,0.214,3.869,-4.652,-8.282,34.642],"bp2_params":[-0.163,-0.200,-0.414,-9.570,3.861,-2.837],"groove_widths":[14.303,11.232,18.628,17.185],"simple_Rise":3.742,"simple_Twist":32.122,"simple_hRise":3.874,"simple_hTwist":32.599},{"index":6,"nt1":"A.DG6","nt2":"C.DC21","bp":"G-C","name":"WC","Saenger":"19-XIX","LW":"cWW","DSSR":"cW-W","bp1_params":[-0.163,-0.200,-0.414,-9.570,3.861,-2.837],"step_params":[1.367,-0.467,6.963,1.583,-1.823,83.804],"heli_params":[-0.257,-0.943,6.990,-1.364,-1.185,83.833],"bp2_params":[0.635,-0.361,0.437,-1.438,-1.044,-4.880],"groove_widths":[13.610,11.224,20.584,18.903],"simple_Rise":6.963,"simple_Twist":79.680,"simple_hRise":6.992,"simple_hTwist":79.710},{"index":7,"nt1":"B.DC8","nt2":"C.DG19","bp":"C-G","name":"WC","Saenger":"19-XIX","LW":"cWW","DSSR":"cW-W","bp1_params":[0.635,-0.361,0.437,-1.438,-1.044,-4.880],"step_params":[0.483,-0.662,3.293,2.195,-10.169,30.882],"heli_params":[0.675,-0.462,3.362,-18.452,-3.982,32.547],"bp2_params":[0.195,-0.240,0.409,5.622,-6.228,-3.007],"groove_widths":[13.866,10.784,22.051,20.571],"simple_Rise":3.293,"simple_Twist":34.102,"simple_hRise":3.370,"simple_hTwist":35.609},{"index":8,"nt1":"B.DT9","nt2":"C.DA18","bp":"T-A","name":"WC","Saenger":"20-XX","LW":"cWW","DSSR":"cW-W","bp1_params":[0.195,-0.240,0.409,5.622,-6.228,-3.007],"step_params":[-0.589,-0.294,3.595,1.410,5.482,35.938],"heli_params":[-1.303,1.158,3.489,8.817,-2.268,36.366],"bp2_params":[-0.115,-0.413,0.535,-4.145,-7.672,-7.367],"groove_widths":[13.039,11.229,14.262,13.842],"simple_Rise":3.595,"simple_Twist":36.843,"simple_hRise":3.493,"simple_hTwist":37.260},{"index":9,"nt1":"B.DT10","nt2":"C.DA17","bp":"T-A","name":"WC","Saenger":"20-XX","LW":"cWW","DSSR":"cW-W","bp1_params":[-0.115,-0.413,0.535,-4.145,-7.672,-7.367],"step_params":[-0.177,0.125,3.022,6.010,-1.625,37.703],"heli_params":[0.380,0.967,2.952,-2.494,-9.223,38.196],"bp2_params":[-0.111,-0.392,0.632,11.291,-17.548,-8.188],"groove_widths":[11.927,null,17.687,null],"simple_Rise":3.022,"simple_Twist":38.513,"simple_hRise":2.955,"simple_hTwist":38.994},{"index":10,"nt1":"B.DG11","nt2":"C.DC16","bp":"G-C","name":"WC","Saenger":"19-XIX","LW":"cWW","DSSR":"cW-W","bp1_params":[-0.111,-0.392,0.632,11.291,-17.548,-8.188],"step_params":[0.710,0.526,3.794,6.168,-1.167,43.665],"heli_params":[0.830,-0.266,3.840,-1.560,-8.242,44.092],"bp2_params":[0.058,-0.319,0.374,-6.773,-17.724,-6.810],"groove_widths":[null,null,null,null],"simple_Rise":3.794,"simple_Twist":41.823,"simple_hRise":3.841,"simple_hTwist":42.271},{"index":11,"nt1":"B.DG12","nt2":"C.DC15","bp":"G-C","name":"WC","Saenger":"19-XIX","LW":"cWW","DSSR":"cW-W","bp1_params":[0.058,-0.319,0.374,-6.773,-17.724,-6.810],"step_params":[-1.625,1.093,3.504,-6.834,-10.400,40.066],"heli_params":[2.695,1.507,3.353,-14.754,9.696,41.878],"bp2_params":[-1.015,-0.780,-0.455,-19.415,-12.084,-17.920],"groove_widths":[null,null,null,null],"simple_Rise":3.504,"simple_Twist":45.043,"simple_hRise":3.385,"simple_hTwist":46.644},{"index":12,"nt1":"B.DG13","nt2":"C.DC14","bp":"G-C","name":"WC","Saenger":"19-XIX","LW":"cWW","DSSR":"cW-W"}]}],"num_stems":2,"stems":[{"index":1,"helix_index":1,"strand1":"CAAGG","strand2":"GTTCC","bp_type":"|||||","helix_form":"BBB.","helical_rise":3.416,"helical_rise_std":0.394,"helical_radius":9.571,"helical_radius_std":0.402,"helical_axis":[-0.046,0.010,0.999],"point1":[0.306,-0.409,2.696],"point2":[-0.321,-0.270,16.438],"num_pairs":5,"pairs":[{"index":1,"nt1":"A.DC2","nt2":"C.DG25","bp":"C-G","name":"WC","Saenger":"19-XIX","LW":"cWW","DSSR":"cW-W","bp1_params":[0.408,-0.204,0.003,-7.719,-0.272,-1.150],"step_params":[-0.313,-0.865,3.358,11.024,3.548,36.590],"heli_params":[-1.763,1.862,3.047,5.485,-17.042,38.319],"bp2_params":[0.188,-0.136,-0.237,-1.591,-15.103,-4.763],"groove_widths":[null,null,null,null],"simple_Rise":3.358,"simple_Twist":36.003,"simple_hRise":3.040,"simple_hTwist":37.761},{"index":2,"nt1":"A.DA3","nt2":"C.DT24","bp":"A-T","name":"WC","Saenger":"20-XX","LW":"cWW","DSSR":"cW-W","bp1_params":[0.188,-0.136,-0.237,-1.591,-15.103,-4.763],"step_params":[0.069,-0.026,2.966,-7.115,-0.722,34.308],"heli_params":[0.056,-1.084,2.894,-1.208,11.902,35.023],"bp2_params":[-0.205,-0.259,0.395,1.925,-11.139,-1.861],"groove_widths":[null,null,null,null],"simple_Rise":2.966,"simple_Twist":37.875,"simple_hRise":2.906,"simple_hTwist":38.520},{"index":3,"nt1":"A.DA4","nt2":"C.DT23","bp":"A-T","name":"WC","Saenger":"20-XX","LW":"cWW","DSSR":"cW-W","bp1_params":[-0.205,-0.259,0.395,1.925,-11.139,-1.861],"step_params":[0.188,-0.727,3.289,-1.930,-4.733,34.593],"heli_params":[-0.483,-0.610,3.342,-7.905,3.224,34.957],"bp2_params":[-0.526,-0.225,0.164,3.992,-8.669,-0.420],"groove_widths":[null,null,null,null],"simple_Rise":3.289,"simple_Twist":36.259,"simple_hRise":3.341,"simple_hTwist":36.605},{"index":4,"nt1":"A.DG5","nt2":"C.DC22","bp":"G-C","name":"WC","Saenger":"19-XIX","LW":"cWW","DSSR":"cW-W","bp1_params":[-0.526,-0.225,0.164,3.992,-8.669,-0.420],"step_params":[0.399,-1.534,3.742,4.911,-2.758,34.195],"heli_params":[-2.080,0.214,3.869,-4.652,-8.282,34.642],"bp2_params":[-0.163,-0.200,-0.414,-9.570,3.861,-2.837],"groove_widths":[null,null,null,null],"simple_Rise":3.742,"simple_Twist":32.122,"simple_hRise":3.874,"simple_hTwist":32.599},{"index":5,"nt1":"A.DG6","nt2":"C.DC21","bp":"G-C","name":"WC","Saenger":"19-XIX","LW":"cWW","DSSR":"cW-W"}]},{"index":2,"helix_index":1,"strand1":"CTTGGG","strand2":"GAACCC","bp_type":"||||||","helix_form":"BBBB.","helical_rise":3.231,"helical_rise_std":0.814,"helical_radius":8.905,"helical_radius_std":1.410,"helical_axis":[-0.052,0.224,0.973],"point1":[1.407,-0.980,23.606],"point2":[0.563,2.662,39.437],"num_pairs":6,"pairs":[{"index":1,"nt1":"B.DC8","nt2":"C.DG19","bp":"C-G","name":"WC","Saenger":"19-XIX","LW":"cWW","DSSR":"cW-W","bp1_params":[0.635,-0.361,0.437,-1.438,-1.044,-4.880],"step_params":[0.483,-0.662,3.293,2.195,-10.169,30.882],"heli_params":[0.675,-0.462,3.362,-18.452,-3.982,32.547],"bp2_params":[0.195,-0.240,0.409,5.622,-6.228,-3.007],"groove_widths":[null,null,null,null],"simple_Rise":3.293,"simple_Twist":34.102,"simple_hRise":3.370,"simple_hTwist":35.609},{"index":2,"nt1":"B.DT9","nt2":"C.DA18","bp":"T-A","name":"WC","Saenger":"20-XX","LW":"cWW","DSSR":"cW-W","bp1_params":[0.195,-0.240,0.409,5.622,-6.228,-3.007],"step_params":[-0.589,-0.294,3.595,1.410,5.482,35.938],"heli_params":[-1.303,1.158,3.489,8.817,-2.268,36.366],"bp2_params":[-0.115,-0.413,0.535,-4.145,-7.672,-7.367],"groove_widths":[null,null,null,null],"simple_Rise":3.595,"simple_Twist":36.843,"simple_hRise":3.493,"simple_hTwist":37.260},{"index":3,"nt1":"B.DT10","nt2":"C.DA17","bp":"T-A","name":"WC","Saenger":"20-XX","LW":"cWW","DSSR":"cW-W","bp1_params":[-0.115,-0.413,0.535,-4.145,-7.672,-7.367],"step_params":[-0.177,0.125,3.022,6.010,-1.625,37.703],"heli_params":[0.380,0.967,2.952,-2.494,-9.223,38.196],"bp2_params":[-0.111,-0.392,0.632,11.291,-17.548,-8.188],"groove_widths":[11.927,null,17.687,null],"simple_Rise":3.022,"simple_Twist":38.513,"simple_hRise":2.955,"simple_hTwist":38.994},{"index":4,"nt1":"B.DG11","nt2":"C.DC16","bp":"G-C","name":"WC","Saenger":"19-XIX","LW":"cWW","DSSR":"cW-W","bp1_params":[-0.111,-0.392,0.632,11.291,-17.548,-8.188],"step_params":[0.710,0.526,3.794,6.168,-1.167,43.665],"heli_params":[0.830,-0.266,3.840,-1.560,-8.242,44.092],"bp2_params":[0.058,-0.319,0.374,-6.773,-17.724,-6.810],"groove_widths":[null,null,null,null],"simple_Rise":3.794,"simple_Twist":41.823,"simple_hRise":3.841,"simple_hTwist":42.271},{"index":5,"nt1":"B.DG12","nt2":"C.DC15","bp":"G-C","name":"WC","Saenger":"19-XIX","LW":"cWW","DSSR":"cW-W","bp1_params":[0.058,-0.319,0.374,-6.773,-17.724,-6.810],"step_params":[-1.625,1.093,3.504,-6.834,-10.400,40.066],"heli_params":[2.695,1.507,3.353,-14.754,9.696,41.878],"bp2_params":[-1.015,-0.780,-0.455,-19.415,-12.084,-17.920],"groove_widths":[null,null,null,null],"simple_Rise":3.504,"simple_Twist":45.043,"simple_hRise":3.385,"simple_hTwist":46.644},{"index":6,"nt1":"B.DG13","nt2":"C.DC14","bp":"G-C","name":"WC","Saenger":"19-XIX","LW":"cWW","DSSR":"cW-W"}]}],"num_coaxStacks":1,"coaxStacks":[{"index":1,"helix_index":1,"num_stems":2,"stem_indices":[1,2]}],"num_stacks":3,"stacks":[{"index":1,"num_nts":2,"nts_short":"CC","nts_long":"A.DC1,A.DC2"},{"index":2,"num_nts":2,"nts_short":"GG","nts_long":"C.DG25,C.DG26"},{"index":3,"num_nts":3,"nts_short":"GGC","nts_long":"C.DG19,C.DG20,C.DC21"}],"num_ssSegments":3,"ssSegments":[{"index":1,"num_nts":1,"nts_short":"C","nts_long":"A.DC1"},{"index":2,"num_nts":1,"nts_short":"G","nts_long":"C.DG20"},{"index":3,"num_nts":1,"nts_short":"G","nts_long":"C.DG26"}],"dbn":{"all_chains":{"num_nts":25,"num_chars":27,"bseq":"CCAAGG&CTTGGG&CCCAAGGCCTTGG","sstr":".(((((&((((((&)))))).))))).","form":"..BB.-&.BBB.-&.BBB....BB..-"},"chain_A":{"num_nts":6,"num_chars":6,"bseq":"CCAAGG","sstr":".(((((","form":"..BB.-"},"chain_B":{"num_nts":6,"num_chars":6,"bseq":"CTTGGG","sstr":"((((((","form":".BBB.-"},"chain_C":{"num_nts":13,"num_chars":13,"bseq":"CCCAAGGCCTTGG","sstr":")))))).))))).","form":".BBB....BB..-"}},"chains":{"chain_A":{"num_nts":6,"bseq":"CCAAGG","sstr":".(((((","form":"..BB.-","helical_rise":3.834,"helical_rise_std":0.326,"helical_axis":[-0.227,0.141,0.964],"point1":[3.359,-0.549,-1.969],"point2":[-1.045,2.191,16.717],"num_chars":16,"suite":"C__C!!A!!A!!G!!G"},"chain_B":{"num_nts":6,"bseq":"CTTGGG","sstr":"((((((","form":".BBB.-","helical_rise":0.221,"helical_rise_std":0.569,"helical_axis":[-0.752,0.186,0.633],"point1":[1.196,4.124,30.620],"point2":[0.965,4.181,30.814],"num_chars":16,"suite":"C__T!!T!!G2[G!!G"},"chain_C":{"num_nts":13,"bseq":"CCCAAGGCCTTGG","sstr":")))))).))))).","form":".BBB....BB..-","helical_rise":3.407,"helical_rise_std":0.546,"helical_axis":[0.074,-0.029,-0.997],"point1":[-1.748,0.784,40.904],"point2":[1.253,-0.405,0.410],"num_chars":37,"suite":"C__C!!C!!A!!A!!G!!G!!C!!C!!T!!T!!G!!G"}},"num_nts":25,"nts":[{"index":1,"index_chain":1,"chain_name":"A","nt_name":"DC","nt_code":"C","nt_id":"A.DC1","dbn":".","summary":"anti,~C2'-endo,BI,non-canonical,non-pair-contact,helix-end,ss-non-loop","alpha":null,"beta":null,"gamma":60.185,"delta":142.608,"epsilon":177.950,"zeta":-97.012,"epsilon_zeta":-85.039,"bb_type":"BI","chi":-139.158,"baseSugar_conf":"anti","form":".","ssZp":1.841,"Dp":2.142,"splay_angle":31.799,"splay_distance":5.002,"splay_ratio":0.274,"eta":null,"theta":null,"eta_prime":null,"theta_prime":null,"eta_base":null,"theta_base":null,"v0":-14.492,"v1":30.885,"v2":-34.673,"v3":25.932,"v4":-7.534,"amplitude":34.888,"phase_angle":173.631,"puckering":"C2'-endo","sugar_class":"~C2'-endo","bin":"inc","cluster":"__","suiteness":0.000,"filter_rmsd":0.079,"frame":{"rsmd":0.046,"origin":[2.189,0.243,-1.067],"x_axis":[-0.834,0.361,-0.418],"y_axis":[-0.280,-0.929,-0.244],"z_axis":[-0.476,-0.086,0.875]}},{"index":2,"index_chain":2,"chain_name":"A","nt_name":"DC","nt_code":"C","nt_id":"A.DC2","dbn":"(","summary":"anti,~C2'-endo,BI,canonical,non-pair-contact,helix,stem-end,coaxial-stack","alpha":-60.969,"beta":178.611,"gamma":70.417,"delta":154.326,"epsilon":178.621,"zeta":-91.808,"epsilon_zeta":-89.571,"bb_type":"BI","chi":-111.931,"baseSugar_conf":"anti","form":".","ssZp":1.465,"Dp":1.866,"splay_angle":18.490,"splay_distance":3.313,"splay_ratio":0.169,"eta":170.966,"theta":-109.891,"eta_prime":-136.457,"theta_prime":-148.134,"eta_base":-77.902,"theta_base":-120.975,"v0":-12.481,"v1":33.254,"v2":-41.134,"v3":34.139,"v4":-14.175,"amplitude":41.142,"phase_angle":181.167,"puckering":"C3'-exo","sugar_class":"~C2'-endo","bin":"22p","cluster":"!!","suiteness":0.000,"filter_rmsd":0.075,"frame":{"rsmd":0.024,"origin":[0.167,-0.574,3.434],"x_axis":[-0.831,-0.552,0.064],"y_axis":[0.543,-0.831,-0.121],"z_axis":[0.121,-0.066,0.991]}},{"index":3,"index_chain":3,"chain_name":"A","nt_name":"DA","nt_code":"A","nt_id":"A.DA3","dbn":"(","summary":"anti,~C2'-endo,BI,canonical,non-pair-contact,helix,stem,coaxial-stack","alpha":-62.462,"beta":-161.816,"gamma":45.783,"delta":128.161,"epsilon":175.949,"zeta":-97.628,"epsilon_zeta":-86.424,"bb_type":"BI","chi":-93.650,"baseSugar_conf":"anti","form":"B","ssZp":0.251,"Dp":2.131,"splay_angle":18.990,"splay_distance":3.298,"splay_ratio":0.168,"eta":-174.623,"theta":-164.298,"eta_prime":-155.235,"theta_prime":-173.170,"eta_base":-125.299,"theta_base":-123.728,"v0":-39.631,"v1":42.010,"v2":-29.322,"v3":7.382,"v4":20.482,"amplitude":42.513,"phase_angle":133.607,"puckering":"C1'-exo","sugar_class":"~C2'-endo","bin":"22p","cluster":"!!","suiteness":0.000,"filter_rmsd":0.056,"frame":{"rsmd":0.041,"origin":[-0.231,0.235,6.622],"x_axis":[-0.380,-0.914,0.144],"y_axis":[0.924,-0.366,0.114],"z_axis":[-0.051,0.176,0.983]}},{"index":4,"index_chain":4,"chain_name":"A","nt_name":"DA","nt_code":"A","nt_id":"A.DA4","dbn":"(","summary":"anti,~C2'-endo,BI,canonical,non-pair-contact,helix,stem,coaxial-stack","alpha":-89.613,"beta":173.144,"gamma":72.305,"delta":131.908,"epsilon":-175.891,"zeta":-81.927,"epsilon_zeta":-93.964,"bb_type":"BI","chi":-110.746,"baseSugar_conf":"anti","form":"B","ssZp":1.803,"Dp":2.213,"splay_angle":18.568,"splay_distance":3.269,"splay_ratio":0.166,"eta":165.415,"theta":-146.155,"eta_prime":-172.051,"theta_prime":-171.892,"eta_base":-123.045,"theta_base":-128.433,"v0":-33.832,"v1":39.925,"v2":-31.688,"v3":12.953,"v4":13.338,"amplitude":39.805,"phase_angle":142.757,"puckering":"C1'-exo","sugar_class":"~C2'-endo","bin":"22p","cluster":"!!","suiteness":0.000,"filter_rmsd":0.046,"frame":{"rsmd":0.027,"origin":[-0.464,0.499,9.902],"x_axis":[0.240,-0.958,0.155],"y_axis":[0.970,0.241,-0.013],"z_axis":[-0.026,0.154,0.988]}},{"index":5,"index_chain":5,"chain_name":"A","nt_name":"DG","nt_code":"G","nt_id":"A.DG5","dbn":"(","summary":"anti,~C2'-endo,BI,canonical,non-pair-contact,helix,stem,coaxial-stack","alpha":-138.880,"beta":112.493,"gamma":149.692,"delta":143.666,"epsilon":-158.776,"zeta":-76.097,"epsilon_zeta":-82.679,"bb_type":"BI","chi":-146.442,"baseSugar_conf":"anti","form":".","ssZp":2.622,"Dp":2.005,"splay_angle":19.744,"splay_distance":3.854,"splay_ratio":0.187,"eta":-165.464,"theta":-159.746,"eta_prime":-167.947,"theta_prime":-157.257,"eta_base":-121.621,"theta_base":-119.931,"v0":-22.516,"v1":34.100,"v2":-33.209,"v3":20.409,"v4":1.019,"amplitude":35.343,"phase_angle":159.987,"puckering":"C2'-endo","sugar_class":"~C2'-endo","bin":"22t","cluster":"!!","suiteness":0.000,"filter_rmsd":0.025,"frame":{"rsmd":0.025,"origin":[-1.078,0.331,13.108],"x_axis":[0.755,-0.632,0.173],"y_axis":[0.651,0.755,-0.081],"z_axis":[-0.080,0.174,0.982]}},{"index":6,"index_chain":6,"chain_name":"A","nt_name":"DG","nt_code":"G","nt_id":"A.DG6","dbn":"(","summary":"anti,canonical,non-pair-contact,helix,stem-end,coaxial-stack","alpha":-77.231,"beta":171.300,"gamma":43.126,"delta":98.709,"epsilon":null,"zeta":null,"epsilon_zeta":null,"bb_type":"..","chi":-143.082,"baseSugar_conf":"anti","form":"-","ssZp":null,"Dp":null,"splay_angle":null,"splay_distance":null,"splay_ratio":null,"eta":null,"theta":null,"eta_prime":null,"theta_prime":null,"eta_base":null,"theta_base":null,"v0":-38.235,"v1":24.621,"v2":-3.547,"v3":-17.918,"v4":36.407,"amplitude":38.239,"phase_angle":95.323,"puckering":"O4'-endo","sugar_class":"....","bin":"23p","cluster":"!!","suiteness":0.000,"filter_rmsd":0.029,"frame":{"rsmd":0.029,"origin":[-1.268,-0.973,16.729],"x_axis":[0.990,-0.129,0.058],"y_axis":[0.136,0.977,-0.165],"z_axis":[-0.035,0.171,0.985]}},{"index":7,"index_chain":1,"chain_name":"B","nt_name":"DC","nt_code":"C","nt_id":"B.DC8","dbn":"(","summary":"anti,~C2'-endo,BI,canonical,non-pair-contact,helix,stem-end,coaxial-stack","alpha":null,"beta":-147.443,"gamma":61.517,"delta":152.373,"epsilon":-157.245,"zeta":-69.220,"epsilon_zeta":-88.026,"bb_type":"BI","chi":-150.154,"baseSugar_conf":"anti","form":".","ssZp":0.659,"Dp":1.510,"splay_angle":18.833,"splay_distance":3.359,"splay_ratio":0.170,"eta":null,"theta":-75.064,"eta_prime":null,"theta_prime":-100.751,"eta_base":null,"theta_base":-73.066,"v0":-9.781,"v1":28.780,"v2":-36.770,"v3":31.017,"v4":-14.676,"amplitude":36.843,"phase_angle":183.606,"puckering":"C3'-exo","sugar_class":"~C2'-endo","bin":"inc","cluster":"__","suiteness":0.000,"filter_rmsd":0.077,"frame":{"rsmd":0.023,"origin":[-0.168,0.351,24.162],"x_axis":[0.250,0.968,-0.019],"y_axis":[-0.963,0.247,-0.110],"z_axis":[-0.102,0.045,0.994]}},{"index":8,"index_chain":2,"chain_name":"B","nt_name":"DT","nt_code":"T","nt_id":"B.DT9","dbn":"(","summary":"anti,~C2'-endo,canonical,non-pair-contact,helix,stem,coaxial-stack","alpha":-103.786,"beta":173.266,"gamma":49.780,"delta":135.929,"epsilon":-164.592,"zeta":171.471,"epsilon_zeta":23.937,"bb_type":"..","chi":-99.055,"baseSugar_conf":"anti","form":"B","ssZp":2.987,"Dp":2.309,"splay_angle":22.955,"splay_distance":3.719,"splay_ratio":0.199,"eta":124.490,"theta":177.218,"eta_prime":176.178,"theta_prime":167.240,"eta_base":-136.860,"theta_base":-150.819,"v0":-32.715,"v1":40.964,"v2":-34.420,"v3":15.554,"v4":10.951,"amplitude":41.091,"phase_angle":146.893,"puckering":"C2'-endo","sugar_class":"~C2'-endo","bin":"22p","cluster":"!!","suiteness":0.000,"filter_rmsd":0.123,"frame":{"rsmd":0.052,"origin":[0.103,0.578,27.503],"x_axis":[-0.306,0.939,0.158],"y_axis":[-0.952,-0.307,-0.024],"z_axis":[0.026,-0.158,0.987]}},{"index":9,"index_chain":3,"chain_name":"B","nt_name":"DT","nt_code":"T","nt_id":"B.DT10","dbn":"(","summary":"anti,~C2'-endo,BI,canonical,non-pair-contact,helix,stem,coaxial-stack","alpha":109.324,"beta":-99.266,"gamma":178.719,"delta":145.044,"epsilon":-149.301,"zeta":-74.982,"epsilon_zeta":-74.320,"bb_type":"BI","chi":-152.685,"baseSugar_conf":"anti","form":"B","ssZp":0.961,"Dp":1.689,"splay_angle":18.075,"splay_distance":3.050,"splay_ratio":0.159,"eta":-158.861,"theta":-114.192,"eta_prime":-146.833,"theta_prime":-137.425,"eta_base":-111.773,"theta_base":-102.803,"v0":-22.554,"v1":35.376,"v2":-35.713,"v3":22.983,"v4":-0.820,"amplitude":37.395,"phase_angle":162.751,"puckering":"C2'-endo","sugar_class":"~C2'-endo","bin":"22t","cluster":"!!","suiteness":0.000,"filter_rmsd":0.111,"frame":{"rsmd":0.041,"origin":[0.557,0.028,31.153],"x_axis":[-0.782,0.622,0.029],"y_axis":[-0.622,-0.776,-0.104],"z_axis":[-0.042,-0.100,0.994]}},{"index":10,"index_chain":4,"chain_name":"B","nt_name":"DG","nt_code":"G","nt_id":"B.DG11","dbn":"(","summary":"anti,~C2'-endo,canonical,non-pair-contact,helix,stem,coaxial-stack","alpha":-96.746,"beta":175.741,"gamma":56.581,"delta":135.748,"epsilon":179.172,"zeta":-165.652,"epsilon_zeta":-15.176,"bb_type":"..","chi":-75.466,"baseSugar_conf":"anti","form":"B","ssZp":1.817,"Dp":2.304,"splay_angle":23.293,"splay_distance":3.798,"splay_ratio":0.202,"eta":131.450,"theta":-169.959,"eta_prime":-176.530,"theta_prime":174.383,"eta_base":-135.152,"theta_base":-124.823,"v0":-31.619,"v1":45.218,"v2":-39.831,"v3":22.006,"v4":5.818,"amplitude":44.439,"phase_angle":153.677,"puckering":"C2'-endo","sugar_class":"~C2'-endo","bin":"22p","cluster":"2[","suiteness":0.010,"filter_rmsd":0.040,"frame":{"rsmd":0.040,"origin":[0.442,-0.008,34.200],"x_axis":[-0.991,0.044,0.123],"y_axis":[-0.023,-0.985,0.168],"z_axis":[0.129,0.164,0.978]}},{"index":11,"index_chain":5,"chain_name":"B","nt_name":"DG","nt_code":"G","nt_id":"B.DG12","dbn":"(","summary":"anti,~C2'-endo,canonical,non-pair-contact,helix,stem,coaxial-stack","alpha":126.933,"beta":-112.184,"gamma":178.415,"delta":141.510,"epsilon":-141.068,"zeta":-148.133,"epsilon_zeta":7.065,"bb_type":"..","chi":-132.326,"baseSugar_conf":"anti","form":".","ssZp":2.122,"Dp":1.828,"splay_angle":22.080,"splay_distance":3.724,"splay_ratio":0.198,"eta":-162.310,"theta":169.816,"eta_prime":-152.460,"theta_prime":161.106,"eta_base":-97.749,"theta_base":-154.533,"v0":-24.311,"v1":34.880,"v2":-33.031,"v3":18.858,"v4":3.108,"amplitude":35.921,"phase_angle":156.862,"puckering":"C2'-endo","sugar_class":"~C2'-endo","bin":"22t","cluster":"!!","suiteness":0.000,"filter_rmsd":0.028,"frame":{"rsmd":0.028,"origin":[-0.296,-0.442,37.901],"x_axis":[-0.732,-0.640,0.234],"y_axis":[0.673,-0.732,0.104],"z_axis":[0.105,0.234,0.967]}},{"index":12,"index_chain":6,"chain_name":"B","nt_name":"DG","nt_code":"G","nt_id":"B.DG13","dbn":"(","summary":"anti,~C2'-endo,canonical,non-pair-contact,helix-end,stem-end,coaxial-stack","alpha":-68.885,"beta":151.389,"gamma":59.680,"delta":134.037,"epsilon":null,"zeta":null,"epsilon_zeta":null,"bb_type":"n/a","chi":-142.016,"baseSugar_conf":"anti","form":"-","ssZp":null,"Dp":null,"splay_angle":null,"splay_distance":null,"splay_ratio":null,"eta":null,"theta":null,"eta_prime":null,"theta_prime":null,"eta_base":null,"theta_base":null,"v0":-8.294,"v1":18.720,"v2":-22.375,"v3":16.281,"v4":-5.630,"amplitude":22.437,"phase_angle":175.762,"puckering":"C2'-endo","sugar_class":"~C2'-endo","bin":"22p","cluster":"4b","suiteness":0.010,"filter_rmsd":0.042,"frame":{"rsmd":0.042,"origin":[1.284,1.678,40.523],"x_axis":[-0.188,-0.886,0.423],"y_axis":[0.933,-0.296,-0.206],"z_axis":[0.308,0.356,0.882]}},{"index":13,"index_chain":1,"chain_name":"C","nt_name":"DC","nt_code":"C","nt_id":"C.DC14","dbn":")","summary":"anti,~C2'-endo,BI,canonical,non-pair-contact,helix-end,stem-end,coaxial-stack","alpha":null,"beta":null,"gamma":169.874,"delta":152.852,"epsilon":-147.498,"zeta":-83.364,"epsilon_zeta":-64.134,"bb_type":"BI","chi":-107.215,"baseSugar_conf":"anti","form":".","ssZp":0.725,"Dp":1.602,"splay_angle":25.308,"splay_distance":4.378,"splay_ratio":0.225,"eta":null,"theta":null,"eta_prime":null,"theta_prime":null,"eta_base":null,"theta_base":null,"v0":-4.288,"v1":22.397,"v2":-31.063,"v3":28.819,"v4":-15.797,"amplitude":31.604,"phase_angle":190.623,"puckering":"C3'-exo","sugar_class":"~C2'-endo","bin":"inc","cluster":"__","suiteness":0.000,"filter_rmsd":0.074,"frame":{"rsmd":0.018,"origin":[2.052,0.757,41.160],"x_axis":[0.087,-0.977,0.193],"y_axis":[-0.996,-0.092,-0.021],"z_axis":[0.039,-0.190,-0.981]}},{"index":14,"index_chain":2,"chain_name":"C","nt_name":"DC","nt_code":"C","nt_id":"C.DC15","dbn":")","summary":"anti,~C2'-endo,BI,canonical,non-pair-contact,helix,stem,coaxial-stack","alpha":-100.981,"beta":84.337,"gamma":154.547,"delta":153.859,"epsilon":-178.851,"zeta":-90.467,"epsilon_zeta":-88.384,"bb_type":"BI","chi":-116.133,"baseSugar_conf":"anti","form":"B","ssZp":0.055,"Dp":1.552,"splay_angle":24.247,"splay_distance":4.006,"splay_ratio":0.210,"eta":-115.584,"theta":142.845,"eta_prime":-127.257,"theta_prime":178.802,"eta_base":-77.856,"theta_base":-118.327,"v0":-7.209,"v1":29.380,"v2":-39.239,"v3":34.758,"v4":-18.530,"amplitude":39.612,"phase_angle":187.873,"puckering":"C3'-exo","sugar_class":"~C2'-endo","bin":"22t","cluster":"!!","suiteness":0.000,"filter_rmsd":0.085,"frame":{"rsmd":0.033,"origin":[-0.010,-0.680,37.575],"x_axis":[-0.633,-0.772,-0.051],"y_axis":[-0.749,0.628,-0.209],"z_axis":[0.194,-0.094,-0.976]}},{"index":15,"index_chain":3,"chain_name":"C","nt_name":"DC","nt_code":"C","nt_id":"C.DC16","dbn":")","summary":"anti,~C2'-endo,BI,canonical,non-pair-contact,helix,stem,coaxial-stack","alpha":-68.808,"beta":-167.363,"gamma":51.034,"delta":153.659,"epsilon":171.945,"zeta":-91.903,"epsilon_zeta":-96.152,"bb_type":"BI","chi":-91.958,"baseSugar_conf":"anti","form":"B","ssZp":-0.252,"Dp":1.825,"splay_angle":17.575,"splay_distance":3.015,"splay_ratio":0.159,"eta":163.338,"theta":-126.970,"eta_prime":-151.928,"theta_prime":-152.946,"eta_base":-99.804,"theta_base":-100.633,"v0":-16.289,"v1":37.170,"v2":-43.542,"v3":34.366,"v4":-11.737,"amplitude":43.608,"phase_angle":176.858,"puckering":"C2'-endo","sugar_class":"~C2'-endo","bin":"22p","cluster":"!!","suiteness":0.000,"filter_rmsd":0.086,"frame":{"rsmd":0.047,"origin":[0.361,-0.442,33.592],"x_axis":[-0.978,-0.116,-0.171],"y_axis":[-0.122,0.992,0.024],"z_axis":[0.167,0.045,-0.985]}},{"index":16,"index_chain":4,"chain_name":"C","nt_name":"DA","nt_code":"A","nt_id":"C.DA17","dbn":")","summary":"anti,~C2'-endo,BI,canonical,non-pair-contact,helix,stem,coaxial-stack","alpha":-66.619,"beta":-159.183,"gamma":26.269,"delta":151.782,"epsilon":175.357,"zeta":-108.777,"epsilon_zeta":-75.867,"bb_type":"BI","chi":-73.888,"baseSugar_conf":"anti","form":"B","ssZp":1.059,"Dp":1.804,"splay_angle":20.992,"splay_distance":3.591,"splay_ratio":0.185,"eta":160.042,"theta":-157.041,"eta_prime":-173.380,"theta_prime":-174.304,"eta_base":-121.817,"theta_base":-123.013,"v0":-19.882,"v1":39.314,"v2":-43.105,"v3":31.675,"v4":-7.857,"amplitude":43.576,"phase_angle":171.569,"puckering":"C2'-endo","sugar_class":"~C2'-endo","bin":"22p","cluster":"!!","suiteness":0.000,"filter_rmsd":0.047,"frame":{"rsmd":0.028,"origin":[0.268,-0.227,30.586],"x_axis":[-0.846,0.522,-0.113],"y_axis":[0.522,0.852,0.027],"z_axis":[0.110,-0.036,-0.993]}},{"index":17,"index_chain":5,"chain_name":"C","nt_name":"DA","nt_code":"A","nt_id":"C.DA18","dbn":")","summary":"anti,~C2'-endo,BI,canonical,non-pair-contact,helix,stem,coaxial-stack","alpha":-81.217,"beta":173.946,"gamma":62.041,"delta":132.612,"epsilon":-178.942,"zeta":-120.255,"epsilon_zeta":-58.687,"bb_type":"BI","chi":-116.895,"baseSugar_conf":"anti","form":".","ssZp":2.844,"Dp":2.289,"splay_angle":20.843,"splay_distance":3.443,"splay_ratio":0.182,"eta":162.637,"theta":-170.055,"eta_prime":-178.338,"theta_prime":177.832,"eta_base":-124.192,"theta_base":-148.884,"v0":-30.328,"v1":38.550,"v2":-31.350,"v3":14.471,"v4":9.767,"amplitude":37.651,"phase_angle":146.372,"puckering":"C2'-endo","sugar_class":"~C2'-endo","bin":"22p","cluster":"!!","suiteness":0.000,"filter_rmsd":0.043,"frame":{"rsmd":0.022,"origin":[-0.043,0.367,27.058],"x_axis":[-0.352,0.935,0.046],"y_axis":[0.931,0.344,0.126],"z_axis":[0.102,0.087,-0.991]}},{"index":18,"index_chain":6,"chain_name":"C","nt_name":"DG","nt_code":"G","nt_id":"C.DG19","dbn":")","summary":"anti,~C2'-endo,BI,canonical,non-pair-contact,helix,stem-end,coaxial-stack","alpha":-71.104,"beta":171.058,"gamma":67.328,"delta":147.309,"epsilon":178.182,"zeta":-104.345,"epsilon_zeta":-77.472,"bb_type":"BI","chi":-130.765,"baseSugar_conf":"anti","form":".","ssZp":2.649,"Dp":2.142,"splay_angle":22.517,"splay_distance":3.756,"splay_ratio":0.200,"eta":164.608,"theta":-126.960,"eta_prime":-163.848,"theta_prime":-163.952,"eta_base":-125.819,"theta_base":-115.601,"v0":-23.765,"v1":38.393,"v2":-37.556,"v3":24.768,"v4":-0.936,"amplitude":39.379,"phase_angle":162.495,"puckering":"C2'-endo","sugar_class":"~C2'-endo","bin":"22p","cluster":"!!","suiteness":0.000,"filter_rmsd":0.033,"frame":{"rsmd":0.033,"origin":[-0.615,-0.217,23.713],"x_axis":[0.169,0.985,-0.045],"y_axis":[0.983,-0.165,0.082],"z_axis":[0.073,-0.058,-0.996]}},{"index":19,"index_chain":7,"chain_name":"C","nt_name":"DG","nt_code":"G","nt_id":"C.DG20","dbn":".","summary":"anti,BI,non-pair-contact,ss-non-loop","alpha":-169.578,"beta":154.603,"gamma":157.445,"delta":110.950,"epsilon":-142.819,"zeta":-97.502,"epsilon_zeta":-45.317,"bb_type":"BI","chi":-154.103,"baseSugar_conf":"anti","form":".","ssZp":3.513,"Dp":4.108,"splay_angle":18.417,"splay_distance":3.143,"splay_ratio":0.169,"eta":179.594,"theta":-146.451,"eta_prime":-178.409,"theta_prime":-142.892,"eta_base":-116.496,"theta_base":-111.022,"v0":10.358,"v1":-15.719,"v2":14.917,"v3":-7.985,"v4":-1.542,"amplitude":16.224,"phase_angle":336.846,"puckering":"C2'-exo","sugar_class":"....","bin":"trig","cluster":"!!","suiteness":0.000,"filter_rmsd":0.027,"frame":{"rsmd":0.027,"origin":[-1.342,0.349,20.073],"x_axis":[0.830,0.489,-0.267],"y_axis":[0.534,-0.836,0.129],"z_axis":[-0.159,-0.250,-0.955]}},{"index":20,"index_chain":8,"chain_name":"C","nt_name":"DC","nt_code":"C","nt_id":"C.DC21","dbn":")","summary":"anti,~C2'-endo,BI,canonical,non-pair-contact,helix,stem-end,coaxial-stack","alpha":163.998,"beta":-162.039,"gamma":161.378,"delta":158.029,"epsilon":165.421,"zeta":-83.085,"epsilon_zeta":-111.494,"bb_type":"BI","chi":-124.985,"baseSugar_conf":"anti","form":".","ssZp":2.112,"Dp":1.730,"splay_angle":25.645,"splay_distance":4.301,"splay_ratio":0.225,"eta":123.758,"theta":-114.651,"eta_prime":-159.486,"theta_prime":-164.581,"eta_base":-120.171,"theta_base":-123.222,"v0":-10.628,"v1":34.172,"v2":-43.785,"v3":38.850,"v4":-18.071,"amplitude":43.962,"phase_angle":185.140,"puckering":"C3'-exo","sugar_class":"~C2'-endo","bin":"trig","cluster":"!!","suiteness":0.000,"filter_rmsd":0.076,"frame":{"rsmd":0.022,"origin":[-1.117,-0.753,17.138],"x_axis":[0.990,-0.073,0.121],"y_axis":[-0.074,-0.997,0.004],"z_axis":[0.120,-0.013,-0.993]}},{"index":21,"index_chain":9,"chain_name":"C","nt_name":"DC","nt_code":"C","nt_id":"C.DC22","dbn":")","summary":"anti,~C2'-endo,BI,canonical,non-pair-contact,helix,stem,coaxial-stack","alpha":-66.279,"beta":-149.823,"gamma":40.207,"delta":148.113,"epsilon":-179.173,"zeta":-90.260,"epsilon_zeta":-88.914,"bb_type":"BI","chi":-120.302,"baseSugar_conf":"anti","form":"B","ssZp":1.516,"Dp":1.918,"splay_angle":19.716,"splay_distance":3.486,"splay_ratio":0.176,"eta":176.034,"theta":-132.228,"eta_prime":-155.859,"theta_prime":-145.006,"eta_base":-106.799,"theta_base":-108.954,"v0":-13.229,"v1":30.968,"v2":-36.537,"v3":29.175,"v4":-10.692,"amplitude":36.565,"phase_angle":177.795,"puckering":"C2'-endo","sugar_class":"~C2'-endo","bin":"22p","cluster":"!!","suiteness":0.000,"filter_rmsd":0.074,"frame":{"rsmd":0.023,"origin":[-0.532,0.138,12.971],"x_axis":[0.760,-0.650,0.023],"y_axis":[-0.645,-0.749,0.150],"z_axis":[-0.080,-0.129,-0.988]}},{"index":22,"index_chain":10,"chain_name":"C","nt_name":"DT","nt_code":"T","nt_id":"C.DT23","dbn":")","summary":"anti,~C2'-endo,BI,canonical,non-pair-contact,helix,stem,coaxial-stack","alpha":-64.378,"beta":-178.261,"gamma":56.297,"delta":126.938,"epsilon":-176.348,"zeta":-92.838,"epsilon_zeta":-83.510,"bb_type":"BI","chi":-119.406,"baseSugar_conf":"anti","form":"B","ssZp":0.716,"Dp":2.317,"splay_angle":15.509,"splay_distance":2.642,"splay_ratio":0.136,"eta":-179.757,"theta":-147.984,"eta_prime":-153.483,"theta_prime":-154.958,"eta_base":-113.346,"theta_base":-118.239,"v0":-31.414,"v1":34.108,"v2":-25.105,"v3":7.502,"v4":15.095,"amplitude":34.563,"phase_angle":136.580,"puckering":"C1'-exo","sugar_class":"~C2'-endo","bin":"22p","cluster":"!!","suiteness":0.000,"filter_rmsd":0.118,"frame":{"rsmd":0.048,"origin":[-0.168,0.342,9.511],"x_axis":[0.269,-0.962,-0.039],"y_axis":[-0.962,-0.270,0.048],"z_axis":[-0.057,0.025,-0.998]}},{"index":23,"index_chain":11,"chain_name":"C","nt_name":"DT","nt_code":"T","nt_id":"C.DT24","dbn":")","summary":"anti,~C2'-endo,BI,canonical,non-pair-contact,helix,stem,coaxial-stack","alpha":-89.431,"beta":-179.754,"gamma":65.238,"delta":144.692,"epsilon":-173.995,"zeta":-98.006,"epsilon_zeta":-75.990,"bb_type":"BI","chi":-82.897,"baseSugar_conf":"anti","form":".","ssZp":2.018,"Dp":2.120,"splay_angle":21.228,"splay_distance":3.654,"splay_ratio":0.190,"eta":154.170,"theta":-147.729,"eta_prime":-169.473,"theta_prime":-179.008,"eta_base":-132.713,"theta_base":-132.661,"v0":-30.084,"v1":45.624,"v2":-44.153,"v3":27.393,"v4":1.723,"amplitude":47.052,"phase_angle":159.785,"puckering":"C2'-endo","sugar_class":"~C2'-endo","bin":"22p","cluster":"!!","suiteness":0.000,"filter_rmsd":0.115,"frame":{"rsmd":0.031,"origin":[-0.067,0.381,6.871],"x_axis":[-0.273,-0.956,-0.107],"y_axis":[-0.948,0.287,-0.140],"z_axis":[0.164,0.063,-0.984]}},{"index":24,"index_chain":12,"chain_name":"C","nt_name":"DG","nt_code":"G","nt_id":"C.DG25","dbn":")","summary":"anti,~C2'-endo,BI,canonical,non-pair-contact,helix,stem-end,coaxial-stack","alpha":-137.416,"beta":104.181,"gamma":152.986,"delta":148.993,"epsilon":173.315,"zeta":-81.356,"epsilon_zeta":-105.330,"bb_type":"BI","chi":-144.016,"baseSugar_conf":"anti","form":".","ssZp":1.935,"Dp":1.913,"splay_angle":30.927,"splay_distance":4.872,"splay_ratio":0.267,"eta":-153.487,"theta":165.338,"eta_prime":-166.415,"theta_prime":-174.862,"eta_base":-120.771,"theta_base":-122.767,"v0":-17.636,"v1":36.114,"v2":-40.017,"v3":30.047,"v4":-8.843,"amplitude":40.307,"phase_angle":173.120,"puckering":"C2'-endo","sugar_class":"~C2'-endo","bin":"22t","cluster":"!!","suiteness":0.000,"filter_rmsd":0.027,"frame":{"rsmd":0.027,"origin":[0.617,-0.514,3.395],"x_axis":[-0.820,-0.569,0.059],"y_axis":[-0.570,0.821,-0.012],"z_axis":[-0.041,-0.043,-0.998]}},{"index":25,"index_chain":13,"chain_name":"C","nt_name":"DG","nt_code":"G","nt_id":"C.DG26","dbn":".","summary":"anti,~C2'-endo,non-canonical,non-pair-contact,helix-end,ss-non-loop","alpha":-72.140,"beta":-146.144,"gamma":53.802,"delta":148.706,"epsilon":null,"zeta":null,"epsilon_zeta":null,"bb_type":"n/a","chi":-103.163,"baseSugar_conf":"anti","form":"-","ssZp":null,"Dp":null,"splay_angle":null,"splay_distance":null,"splay_ratio":null,"eta":null,"theta":null,"eta_prime":null,"theta_prime":null,"eta_base":null,"theta_base":null,"v0":-2.566,"v1":19.236,"v2":-28.051,"v3":26.542,"v4":-15.871,"amplitude":28.840,"phase_angle":193.427,"puckering":"C3'-exo","sugar_class":"~C2'-endo","bin":"22p","cluster":"!!","suiteness":0.000,"filter_rmsd":0.030,"frame":{"rsmd":0.030,"origin":[1.145,-0.944,-1.428],"x_axis":[-0.883,0.223,-0.413],"y_axis":[0.164,0.971,0.174],"z_axis":[0.440,0.086,-0.894]}}],"num_hbonds":38,"hbonds":[{"index":1,"atom1_serNum":11,"atom2_serNum":35,"donAcc_type":"questionable","distance":2.895,"atom1_id":"O2@A.DC1","atom2_id":"O4'@A.DC2","atom_pair":"O:O","residue_pair":"nt:nt"},{"index":2,"atom1_serNum":12,"atom2_serNum":779,"donAcc_type":"standard","distance":2.348,"atom1_id":"N3@A.DC1","atom2_id":"N2@C.DG26","atom_pair":"N:N","residue_pair":"nt:nt"},{"index":3,"atom1_serNum":42,"atom2_serNum":746,"donAcc_type":"standard","distance":2.667,"atom1_id":"O2@A.DC2","atom2_id":"N2@C.DG25","atom_pair":"O:N","residue_pair":"nt:nt"},{"index":4,"atom1_serNum":43,"atom2_serNum":744,"donAcc_type":"standard","distance":2.876,"atom1_id":"N3@A.DC2","atom2_id":"N1@C.DG25","atom_pair":"N:N","residue_pair":"nt:nt"},{"index":5,"atom1_serNum":45,"atom2_serNum":743,"donAcc_type":"standard","distance":2.884,"atom1_id":"N4@A.DC2","atom2_id":"O6@C.DG25","atom_pair":"N:O","residue_pair":"nt:nt"},{"index":6,"atom1_serNum":75,"atom2_serNum":711,"donAcc_type":"standard","distance":2.781,"atom1_id":"N6@A.DA3","atom2_id":"O4@C.DT24","atom_pair":"N:O","residue_pair":"nt:nt"},{"index":7,"atom1_serNum":76,"atom2_serNum":709,"donAcc_type":"standard","distance":2.876,"atom1_id":"N1@A.DA3","atom2_id":"N3@C.DT24","atom_pair":"N:N","residue_pair":"nt:nt"},{"index":8,"atom1_serNum":107,"atom2_serNum":679,"donAcc_type":"standard","distance":2.810,"atom1_id":"N6@A.DA4","atom2_id":"O4@C.DT23","atom_pair":"N:O","residue_pair":"nt:nt"},{"index":9,"atom1_serNum":108,"atom2_serNum":677,"donAcc_type":"standard","distance":2.799,"atom1_id":"N1@A.DA4","atom2_id":"N3@C.DT23","atom_pair":"N:N","residue_pair":"nt:nt"},{"index":10,"atom1_serNum":139,"atom2_serNum":649,"donAcc_type":"standard","distance":2.933,"atom1_id":"O6@A.DG5","atom2_id":"N4@C.DC22","atom_pair":"O:N","residue_pair":"nt:nt"},{"index":11,"atom1_serNum":140,"atom2_serNum":647,"donAcc_type":"standard","distance":2.890,"atom1_id":"N1@A.DG5","atom2_id":"N3@C.DC22","atom_pair":"N:N","residue_pair":"nt:nt"},{"index":12,"atom1_serNum":142,"atom2_serNum":646,"donAcc_type":"standard","distance":2.659,"atom1_id":"N2@A.DG5","atom2_id":"O2@C.DC22","atom_pair":"N:O","residue_pair":"nt:nt"},{"index":13,"atom1_serNum":142,"atom2_serNum":669,"donAcc_type":"standard","distance":3.560,"atom1_id":"N2@A.DG5","atom2_id":"O4'@C.DT23","atom_pair":"N:O","residue_pair":"nt:nt"},{"index":14,"atom1_serNum":172,"atom2_serNum":619,"donAcc_type":"standard","distance":2.846,"atom1_id":"O6@A.DG6","atom2_id":"N4@C.DC21","atom_pair":"O:N","residue_pair":"nt:nt"},{"index":15,"atom1_serNum":173,"atom2_serNum":617,"donAcc_type":"standard","distance":2.853,"atom1_id":"N1@A.DG6","atom2_id":"N3@C.DC21","atom_pair":"N:N","residue_pair":"nt:nt"},{"index":16,"atom1_serNum":175,"atom2_serNum":616,"donAcc_type":"standard","distance":2.672,"atom1_id":"N2@A.DG6","atom2_id":"O2@C.DC21","atom_pair":"N:O","residue_pair":"nt:nt"},{"index":17,"atom1_serNum":175,"atom2_serNum":639,"donAcc_type":"standard","distance":3.378,"atom1_id":"N2@A.DG6","atom2_id":"O4'@C.DC22","atom_pair":"N:O","residue_pair":"nt:nt"},{"index":18,"atom1_serNum":204,"atom2_serNum":556,"donAcc_type":"standard","distance":2.731,"atom1_id":"O2@B.DC8","atom2_id":"N2@C.DG19","atom_pair":"O:N","residue_pair":"nt:nt"},{"index":19,"atom1_serNum":205,"atom2_serNum":554,"donAcc_type":"standard","distance":2.896,"atom1_id":"N3@B.DC8","atom2_id":"N1@C.DG19","atom_pair":"N:N","residue_pair":"nt:nt"},{"index":20,"atom1_serNum":207,"atom2_serNum":553,"donAcc_type":"standard","distance":2.793,"atom1_id":"N4@B.DC8","atom2_id":"O6@C.DG19","atom_pair":"N:O","residue_pair":"nt:nt"},{"index":21,"atom1_serNum":235,"atom2_serNum":522,"donAcc_type":"standard","distance":2.847,"atom1_id":"N3@B.DT9","atom2_id":"N1@C.DA18","atom_pair":"N:N","residue_pair":"nt:nt"},{"index":22,"atom1_serNum":237,"atom2_serNum":521,"donAcc_type":"standard","distance":2.865,"atom1_id":"O4@B.DT9","atom2_id":"N6@C.DA18","atom_pair":"O:N","residue_pair":"nt:nt"},{"index":23,"atom1_serNum":267,"atom2_serNum":490,"donAcc_type":"standard","distance":2.671,"atom1_id":"N3@B.DT10","atom2_id":"N1@C.DA17","atom_pair":"N:N","residue_pair":"nt:nt"},{"index":24,"atom1_serNum":269,"atom2_serNum":489,"donAcc_type":"standard","distance":2.516,"atom1_id":"O4@B.DT10","atom2_id":"N6@C.DA17","atom_pair":"O:N","residue_pair":"nt:nt"},{"index":25,"atom1_serNum":301,"atom2_serNum":459,"donAcc_type":"standard","distance":2.597,"atom1_id":"O6@B.DG11","atom2_id":"N4@C.DC16","atom_pair":"O:N","residue_pair":"nt:nt"},{"index":26,"atom1_serNum":302,"atom2_serNum":457,"donAcc_type":"standard","distance":2.746,"atom1_id":"N1@B.DG11","atom2_id":"N3@C.DC16","atom_pair":"N:N","residue_pair":"nt:nt"},{"index":27,"atom1_serNum":304,"atom2_serNum":456,"donAcc_type":"standard","distance":2.772,"atom1_id":"N2@B.DG11","atom2_id":"O2@C.DC16","atom_pair":"N:O","residue_pair":"nt:nt"},{"index":28,"atom1_serNum":334,"atom2_serNum":429,"donAcc_type":"standard","distance":2.723,"atom1_id":"O6@B.DG12","atom2_id":"N4@C.DC15","atom_pair":"O:N","residue_pair":"nt:nt"},{"index":29,"atom1_serNum":335,"atom2_serNum":427,"donAcc_type":"standard","distance":2.778,"atom1_id":"N1@B.DG12","atom2_id":"N3@C.DC15","atom_pair":"N:N","residue_pair":"nt:nt"},{"index":30,"atom1_serNum":337,"atom2_serNum":426,"donAcc_type":"standard","distance":2.676,"atom1_id":"N2@B.DG12","atom2_id":"O2@C.DC15","atom_pair":"N:O","residue_pair":"nt:nt"},{"index":31,"atom1_serNum":367,"atom2_serNum":398,"donAcc_type":"standard","distance":2.260,"atom1_id":"O6@B.DG13","atom2_id":"N4@C.DC14","atom_pair":"O:N","residue_pair":"nt:nt"},{"index":32,"atom1_serNum":368,"atom2_serNum":396,"donAcc_type":"standard","distance":2.803,"atom1_id":"N1@B.DG13","atom2_id":"N3@C.DC14","atom_pair":"N:N","residue_pair":"nt:nt"},{"index":33,"atom1_serNum":370,"atom2_serNum":395,"donAcc_type":"standard","distance":3.057,"atom1_id":"N2@B.DG13","atom2_id":"O2@C.DC14","atom_pair":"N:O","residue_pair":"nt:nt"},{"index":34,"atom1_serNum":426,"atom2_serNum":449,"donAcc_type":"questionable","distance":3.051,"atom1_id":"O2@C.DC15","atom2_id":"O4'@C.DC16","atom_pair":"O:O","residue_pair":"nt:nt"},{"index":35,"atom1_serNum":456,"atom2_serNum":479,"donAcc_type":"questionable","distance":2.892,"atom1_id":"O2@C.DC16","atom2_id":"O4'@C.DA17","atom_pair":"O:O","residue_pair":"nt:nt"},{"index":36,"atom1_serNum":616,"atom2_serNum":639,"donAcc_type":"questionable","distance":3.062,"atom1_id":"O2@C.DC21","atom2_id":"O4'@C.DC22","atom_pair":"O:O","residue_pair":"nt:nt"},{"index":37,"atom1_serNum":646,"atom2_serNum":669,"donAcc_type":"questionable","distance":3.053,"atom1_id":"O2@C.DC22","atom2_id":"O4'@C.DT23","atom_pair":"O:O","residue_pair":"nt:nt"},{"index":38,"atom1_serNum":746,"atom2_serNum":766,"donAcc_type":"standard","distance":3.253,"atom1_id":"N2@C.DG25","atom2_id":"O4'@C.DG26","atom_pair":"N:O","residue_pair":"nt:nt"}],"refCoords":{"purine":["   12 ATOMS,    12 BONDS","    1 N      -2.2500   5.0000   0.2500","    2 N      -2.2500   0.5000   0.2500","    3 N      -2.2500   0.5000  -0.2500","    4 N      -2.2500   5.0000  -0.2500","    5 C       2.2500   5.0000   0.2500","    6 C       2.2500   0.5000   0.2500","    7 C       2.2500   0.5000  -0.2500","    8 C       2.2500   5.0000  -0.2500","    9 C      -2.2500   5.0000   0.2500","   10 C      -2.2500   0.5000   0.2500","   11 C      -2.2500   0.5000  -0.2500","   12 C      -2.2500   5.0000  -0.2500","    1     1     2","    2     2     3","    3     3     4","    4     4     1","    5     5     6","    6     6     7","    7     7     8","    8     5     8","    9     9     5","   10    10     6","   11    11     7","   12    12     8"],"pyrimidine":["   12 ATOMS,    12 BONDS","    1 N      -2.2500   5.0000   0.2500","    2 N      -2.2500   2.0000   0.2500","    3 N      -2.2500   2.0000  -0.2500","    4 N      -2.2500   5.0000  -0.2500","    5 C       2.2500   5.0000   0.2500","    6 C       2.2500   2.0000   0.2500","    7 C       2.2500   2.0000  -0.2500","    8 C       2.2500   5.0000  -0.2500","    9 C      -2.2500   5.0000   0.2500","   10 C      -2.2500   2.0000   0.2500","   11 C      -2.2500   2.0000  -0.2500","   12 C      -2.2500   5.0000  -0.2500","    1     1     2","    2     2     3","    3     3     4","    4     4     1","    5     5     6","    6     6     7","    7     7     8","    8     5     8","    9     9     5","   10    10     6","   11    11     7","   12    12     8"],"wc_pair":["   12 ATOMS,    12 BONDS","    1 N      -2.2500   5.0000   0.2500","    2 N      -2.2500  -5.0000   0.2500","    3 N      -2.2500  -5.0000  -0.2500","    4 N      -2.2500   5.0000  -0.2500","    5 C       2.2500   5.0000   0.2500","    6 C       2.2500  -5.0000   0.2500","    7 C       2.2500  -5.0000  -0.2500","    8 C       2.2500   5.0000  -0.2500","    9 C      -2.2500   5.0000   0.2500","   10 C      -2.2500  -5.0000   0.2500","   11 C      -2.2500  -5.0000  -0.2500","   12 C      -2.2500   5.0000  -0.2500","    1     1     2","    2     2     3","    3     3     4","    4     4     1","    5     5     6","    6     6     7","    7     7     8","    8     5     8","    9     9     5","   10    10     6","   11    11     7","   12    12     8"]},"metadata":{"version":"DSSR v1.6.5-2017jan22 by xiangjun@x3dna.org","manual":"http://x3dna.bio.columbia.edu/docs/dssr-manual.pdf","url":"http://x3dna.org","url_alt":"http://home.x3dna.org","forum":"http://forum.x3dna.org","citation":"Lu et al. (2015). 'DSSR: an integrated software tool for dissecting the spatial structure of RNA.' Nucleic Acids Res., 43(21):e142 [doi:10.1093/nar/gkv716].","command":"x3dna-dssr -i=./Nmr/1n0k.pdb --json --more -o=1n0k.json","input_file":"./Nmr/1n0k.pdb","str_id":"1n0k","num_naChains":3,"naChains":"A=6,B=6,C=13","num_atoms":800,"num_waters":0,"num_notes":52,"notes":[{"Aminors":"A-minor interactions (including types I and II)"},{"Cstem_index":"stem index of the 'Canonical' helix in k-turn"},{"Cstem_pair":"Cstem bp delineating the k-turn internal loop"},{"Dp":"perpendicular distance of the 3' P atom to the glycosidic bond"},{"GA_pair":"sheared G-A pair in k-turn"},{"HtypePknot":"H-type pseudoknot"},{"Kturn":"kink-turn (k-turn)"},{"LW":"Leontis-Westhof"},{"NCstem_index":"stem index of the 'Non-Canonical' helix in k-turn"},{"NCstem_pair":"NCstem bp delineating the k-turn internal loop"},{"Uturn":"U-turn of the UNR- or GNRA-type"},{"aa":"amino acid"},{"atom_pair":"symbols of the two atoms involved in an H-bond"},{"auxfiles":"auxiliary files"},{"baseSugar_conf":"conformation of base related to sugar (syn or anti)"},{"bb_type":"backbone conformation, BI or BII"},{"bending_angle":"angle between two helical axes"},{"bp":"base pair"},{"bseq":"base sequence in one-letter code"},{"bulge":"bulge loop"},{"coaxStacks":"coaxial stacking of stems within a helix"},{"dbn":"dot bracket notation"},{"desc":"description"},{"donAcc_type":"donor/acceptor type of the atom pair in an H-bond"},{"epsilon_zeta":"difference between epsilon and zeta torsion angles"},{"hairpin":"hairpin loop"},{"hbond":"hydrogen bond (H-bond)"},{"helix":"defined by base-stacking interactions, regardless of bp type and backbone connectivity"},{"id":"identifier"},{"iloop":"internal loop"},{"index":"serial number"},{"isoCanonPairs":"isolated canonical pairs"},{"junction":"(multi-branched) junction loop"},{"kissingLoop":"kissing loop"},{"multiplet":"3+ bases in a coplanar geometry"},{"na":"nucleic acid"},{"nonPair":"two nts not forming a pair, but with H-bonding/stacking interactions"},{"nonStack":"nucleotide not involved in stacking interactions"},{"nt":"nucleotide"},{"num":"number"},{"oArea":"overlap areas between two bases, including exocyclic atoms"},{"oArea_ring":"overlap areas between two bases, including only ring atoms"},{"phosContacts":"H-bonding and atom-capping interactions involving a phosphate"},{"residue_pair":"types of the two residues involved in an H-bond"},{"rmsd":"root-mean-squares deviation"},{"serNum":"serial number"},{"ssSegments":"single-stranded segments not involved in loops"},{"ssZp":"Z-coordinate of the 3' phosphorus atom with reference to the 5' base plane"},{"sstr":"secondary structure in dbn"},{"stem":"helix consisting of only canonical pairs, with a continuous backbone"},{"str_id":"structure identifier, derived from inpfile with extension removed"},{"vert_dist":"vertical distance from an atom to a base plane"}],"num_auxfiles":8,"auxfiles":[{"index":1,"name":"dssr-stems.pdb","desc":"an ensemble of stems"},{"index":2,"name":"dssr-helices.pdb","desc":"an ensemble of helices (coaxial stacking)"},{"index":3,"name":"dssr-pairs.pdb","desc":"an ensemble of base pairs"},{"index":4,"name":"dssr-2ndstrs.bpseq","desc":"secondary structure in bpseq format"},{"index":5,"name":"dssr-2ndstrs.ct","desc":"secondary structure in connectivity table format"},{"index":6,"name":"dssr-2ndstrs.dbn","desc":"secondary structure in dot-bracket notation"},{"index":7,"name":"dssr-torsions.txt","desc":"backbone torsion angles and suite names"},{"index":8,"name":"dssr-stacks.pdb","desc":"an ensemble of stacks"}],"start_at":"Mon Oct 16 19:49:55 2017","finish_at":"Mon Oct 16 19:49:55 2017","time_used":"00:00:00:00"}}